inveniordm_py/__init__.py
inveniordm_py/client.py
inveniordm_py/metadata.py
inveniordm_py/pagination.py
inveniordm_py/resources.py
inveniordm_py/files/__init__.py
inveniordm_py/files/metadata.py
inveniordm_py/records/__init__.py
inveniordm_py/records/metadata.py
inveniordm_py/records/resources.py
tests/__init__.py
tests/conftest.py
tests/test_drafts.py
tests/test_files.py
tests/test_invenio_client.py
tests/mock/__init__.py
tests/mock/handlers.py
tests/mock/request.py
tests/mock/response.py
tests/mock/session.py
inveniordm_py-0.1.1.dist-info/AUTHORS.rst
inveniordm_py-0.1.1.dist-info/LICENSE
inveniordm_py-0.1.1.dist-info/METADATA
inveniordm_py-0.1.1.dist-info/WHEEL
inveniordm_py-0.1.1.dist-info/top_level.txt
inveniordm_py-0.1.1.dist-info/RECORD
