Metadata-Version: 2.1
Name: inveniordm-py
Version: 0.1.1
Summary: "Invenio REST API client."
Home-page: https://github.com/inveniosoftware/inveniordm-py
Author: CERN
Author-email: info@inveniosoftware.org
License: MIT
Keywords: invenio rest api
Platform: any
Classifier: Development Status :: 1 - Planning
Requires-Python: >=3.7
Requires-Dist: requests >=2.8
Provides-Extra: tests
Requires-Dist: pytest-invenio <3.0.0,>=2.1.0 ; extra == 'tests'
Requires-Dist: pytest-black >=0.3.0 ; extra == 'tests'
Requires-Dist: sphinx >=4.5.0 ; extra == 'tests'
